pivotalpath/__init__.py
pivotalpath/version.py
pivotalpath/cli/__init__.py
pivotalpath/core/__init__.py
pivotalpath/core/examples.py
pivotalpath/core/important_tickers.py
pivotalpath/core/main_library.py
pivotalpath/data/__init__.py
pivotalpath/data/api.py
pivotalpath/data/utils.py
pivotalpath/llm/__init__.py
pivotalpath/llm/interface.py
pivotalpath/stats/__init__.py
pivotalpath/stats/catalog.py
pivotalpath/stats/kernel.py
pivotalpath/stats/params.py
pivotalpath/stats/wrapper.py
pivotalpath-1.0.6.dist-info/METADATA
pivotalpath-1.0.6.dist-info/WHEEL
pivotalpath-1.0.6.dist-info/top_level.txt
pivotalpath-1.0.6.dist-info/RECORD
