Metadata-Version: 2.1
Name: pivotalpath
Version: 1.0.6
Summary: The industry standard for hedge fund index analytics
Author-email: Your Name <your.email@example.com>
License: MIT
Requires-Python: >=3.7
Requires-Dist: pandas >=1.3.0
Requires-Dist: numpy >=1.20.0
Requires-Dist: requests >=2.25.0
Requires-Dist: python-dateutil >=2.8.0
